sqlalchemy_loadump/__init__.py
sqlalchemy_loadump/__main__.py
sqlalchemy_loadump/cli.py
sqlalchemy_loadump/dumper.py
sqlalchemy_loadump/exporter/__init__.py
sqlalchemy_loadump/exporter/exporter.py
sqlalchemy_loadump/exporter/json_exporter.py
sqlalchemy_loadump/exporter_switcher.py
sqlalchemy_loadump/importer/__init__.py
sqlalchemy_loadump/importer/importer.py
sqlalchemy_loadump/importer/json_importer.py
sqlalchemy_loadump/importer_switcher.py
sqlalchemy_loadump/loader.py
sqlalchemy_loadump/version.py
sqlalchemy_loadump-0.2.0.dist-info/LICENSE
sqlalchemy_loadump-0.2.0.dist-info/METADATA
sqlalchemy_loadump-0.2.0.dist-info/WHEEL
sqlalchemy_loadump-0.2.0.dist-info/RECORD
