Metadata-Version: 2.1
Name: sqlalchemy-loadump
Version: 0.2.0
Summary: This library makes your software to dump and load data in databases with sqlalchemy.
Home-page: https://github.com/wintermaples/sqlalchemy-loadump
License: Apache-2.0
Author: wintermaples
Author-email: pg.wintermaples@gmail.com
Requires-Python: >=3.8,<4.0
Classifier: Development Status :: 3 - Alpha
Classifier: Environment :: Console
Classifier: License :: OSI Approved :: Apache Software License
Classifier: Programming Language :: Python :: 3
Classifier: Programming Language :: Python :: 3.8
Classifier: Programming Language :: Python :: 3.9
Classifier: Programming Language :: Python :: 3.10
Classifier: Programming Language :: Python :: 3.11
Classifier: Topic :: Database
Classifier: Topic :: Utilities
Requires-Dist: sqlalchemy (>=2.0,<3.0)
Project-URL: Repository, https://github.com/wintermaples/sqlalchemy-loadump
